naclfile/__init__.py
naclfile/tar.py
naclfile/zstd.py
naclfile-0.0.6.dist-info/METADATA
naclfile-0.0.6.dist-info/WHEEL
naclfile-0.0.6.dist-info/entry_points.txt
naclfile-0.0.6.dist-info/licenses/LICENSE
naclfile-0.0.6.dist-info/RECORD
