Metadata-Version: 2.4
Name: naclfile
Version: 0.0.6
Summary: A python xxxFile like (ie GzipFile, BZ2File, ...) for manipulating Nacl encrypted files.
Project-URL: HomePage, https://github.com/bibi21000/NaclFile
Project-URL: Issues, https://github.com/bibi21000/NaclFile/issues
Project-URL: Changelog, https://github.com/bibi21000/NaclFile/blob/master/CHANGELOG.md
Project-URL: Documentation, https://bibi21000.github.io/NaclFile/
Author-email: bibi21000 <bibi21000@gmail.com>
Maintainer-email: bibi21000 <bibi21000@gmail.com>
License-File: LICENSE
Classifier: Development Status :: 4 - Beta
Classifier: Intended Audience :: Developers
Classifier: License :: OSI Approved :: MIT License
Classifier: Operating System :: OS Independent
Classifier: Programming Language :: Python :: 3
Classifier: Programming Language :: Python :: 3.9
Classifier: Programming Language :: Python :: 3.10
Classifier: Programming Language :: Python :: 3.11
Classifier: Programming Language :: Python :: 3.12
Classifier: Topic :: Software Development :: Libraries :: Python Modules
Requires-Python: >=3.9
Requires-Dist: cofferfile
Requires-Dist: pynacl
Provides-Extra: build
Requires-Dist: build; extra == 'build'
Requires-Dist: twine; extra == 'build'
Provides-Extra: doc
Requires-Dist: pdoc; extra == 'doc'
Provides-Extra: test
Requires-Dist: bandit; extra == 'test'
Requires-Dist: coverage[toml]; extra == 'test'
Requires-Dist: pytest; extra == 'test'
Requires-Dist: pytest-cov; extra == 'test'
Requires-Dist: pytest-mock; extra == 'test'
Requires-Dist: pytest-random-order; extra == 'test'
Requires-Dist: pytest-xdist; extra == 'test'
Requires-Dist: ruff; extra == 'test'
Provides-Extra: zstd
Requires-Dist: pyzstd; extra == 'zstd'
